<FlowChart xmlns="http://www.EZL.com//FlowChart" xmlns:xsi="http://www.w3.org/2001/XMLSchema-instance" xsi:schemaLocation="FlowChart.xsd"><Files xmlns=""><File id="F_17" Name="C:\IBM AD\Mainframe Projects\clientCobol\zOS Cobol\LGICVS01.cbl"/></Files><Sections xmlns=""><Section Name="MAINLINE"><StartPos FileId="F_17" Row="107" Column="8"/><EndPos FileId="F_17" Row="107" Column="16"/><Paragraph id="P_51" Name="MAINLINE_FIRST_SENTENCES" FallThrough="0"><StartPos FileId="F_17" Row="107" Column="8"/><EndPos FileId="F_17" Row="107" Column="16"/><Statements><Statement><StartPos FileId="F_17" Row="109" Column="12"/><EndPos FileId="F_17" Row="109" Column="34"/></Statement><Statement><StartPos FileId="F_17" Row="111" Column="22"/><EndPos FileId="F_17" Row="112" Column="30"/></Statement><Statement><StartPos FileId="F_17" Row="115" Column="22"/><EndPos FileId="F_17" Row="116" Column="30"/></Statement><Statement><StartPos FileId="F_17" Row="119" Column="22"/><EndPos FileId="F_17" Row="120" Column="30"/></Statement><IfStatement><StartPos FileId="F_17" Row="122" Column="12"/><EndPos FileId="F_17" Row="123" Column="41"/><Then><Statement><StartPos FileId="F_17" Row="124" Column="15"/><EndPos FileId="F_17" Row="124" Column="34"/></Statement><Statement><StartPos FileId="F_17" Row="125" Column="15"/><EndPos FileId="F_17" Row="125" Column="46"/></Statement><Statement><StartPos FileId="F_17" Row="126" Column="15"/><EndPos FileId="F_17" Row="126" Column="46"/></Statement></Then><Else><Statement><StartPos FileId="F_17" Row="128" Column="25"/><EndPos FileId="F_17" Row="130" Column="32"/></Statement><Statement><StartPos FileId="F_17" Row="132" Column="15"/><EndPos FileId="F_17" Row="132" Column="34"/></Statement><Statement><StartPos FileId="F_17" Row="133" Column="15"/><EndPos FileId="F_17" Row="133" Column="48"/></Statement><Statement><StartPos FileId="F_17" Row="134" Column="15"/><EndPos FileId="F_17" Row="134" Column="42"/></Statement></Else></IfStatement><Statement><StartPos FileId="F_17" Row="137" Column="12"/><EndPos FileId="F_17" Row="137" Column="42"/></Statement><Statement><StartPos FileId="F_17" Row="138" Column="12"/><EndPos FileId="F_17" Row="138" Column="43"/></Statement><Statement><StartPos FileId="F_17" Row="139" Column="12"/><EndPos FileId="F_17" Row="139" Column="43"/></Statement><Statement><StartPos FileId="F_17" Row="140" Column="12"/><EndPos FileId="F_17" Row="140" Column="43"/></Statement><Statement><StartPos FileId="F_17" Row="141" Column="12"/><EndPos FileId="F_17" Row="141" Column="43"/></Statement><Statement><StartPos FileId="F_17" Row="143" Column="22"/><EndPos FileId="F_17" Row="144" Column="53"/></Statement><Statement><StartPos FileId="F_17" Row="146" Column="22"/><EndPos FileId="F_17" Row="149" Column="29"/></Statement><IfStatement><StartPos FileId="F_17" Row="151" Column="12"/><EndPos FileId="F_17" Row="151" Column="40"/><Then><Statement><StartPos FileId="F_17" Row="152" Column="15"/><EndPos FileId="F_17" Row="152" Column="41"/></Statement><DoWhileState><StartPos FileId="F_17" Row="153" Column="23"/><EndPos FileId="F_17" Row="154" Column="27"/><Statements><Statement><StartPos FileId="F_17" Row="154" Column="28"/><EndPos FileId="F_17" Row="157" Column="26"/></Statement><IfStatement><StartPos FileId="F_17" Row="159" Column="18"/><EndPos FileId="F_17" Row="160" Column="58"/><Then><Statement><StartPos FileId="F_17" Row="161" Column="23"/><EndPos FileId="F_17" Row="161" Column="56"/></Statement><Statement><StartPos FileId="F_17" Row="162" Column="23"/><EndPos FileId="F_17" Row="162" Column="49"/></Statement></Then></IfStatement><IfStatement><StartPos FileId="F_17" Row="164" Column="18"/><EndPos FileId="F_17" Row="165" Column="59"/><Then><Statement><StartPos FileId="F_17" Row="166" Column="23"/><EndPos FileId="F_17" Row="166" Column="58"/></Statement><Statement><StartPos FileId="F_17" Row="167" Column="23"/><EndPos FileId="F_17" Row="167" Column="49"/></Statement></Then></IfStatement></Statements></DoWhileState></Then></IfStatement><Statement><StartPos FileId="F_17" Row="172" Column="12"/><EndPos FileId="F_17" Row="172" Column="45"/></Statement><Statement><StartPos FileId="F_17" Row="173" Column="12"/><EndPos FileId="F_17" Row="173" Column="47"/></Statement><IfStatement><StartPos FileId="F_17" Row="176" Column="12"/><EndPos FileId="F_17" Row="177" Column="23"/><Then><Statement><StartPos FileId="F_17" Row="177" Column="24"/><EndPos FileId="F_17" Row="181" Column="34"/></Statement></Then></IfStatement><IfStatement><StartPos FileId="F_17" Row="185" Column="12"/><EndPos FileId="F_17" Row="186" Column="23"/><Then><Statement><StartPos FileId="F_17" Row="186" Column="24"/><EndPos FileId="F_17" Row="190" Column="34"/></Statement></Then></IfStatement><IfStatement><StartPos FileId="F_17" Row="194" Column="12"/><EndPos FileId="F_17" Row="195" Column="23"/><Then><Statement><StartPos FileId="F_17" Row="195" Column="24"/><EndPos FileId="F_17" Row="199" Column="34"/></Statement></Then></IfStatement><Statement><StartPos FileId="F_17" Row="203" Column="22"/><EndPos FileId="F_17" Row="204" Column="53"/></Statement><Statement><StartPos FileId="F_17" Row="207" Column="12"/><EndPos FileId="F_17" Row="210" Column="39"/></Statement><Statement><StartPos FileId="F_17" Row="211" Column="12"/><EndPos FileId="F_17" Row="211" Column="51"/></Statement><Statement><StartPos FileId="F_17" Row="213" Column="22"/><EndPos FileId="F_17" Row="219" Column="26"/></Statement><IfStatement><StartPos FileId="F_17" Row="221" Column="12"/><EndPos FileId="F_17" Row="221" Column="40"/><Then><Statement><StartPos FileId="F_17" Row="222" Column="14"/><EndPos FileId="F_17" Row="222" Column="52"/></Statement></Then></IfStatement><IfStatement><StartPos FileId="F_17" Row="225" Column="12"/><EndPos FileId="F_17" Row="226" Column="23"/><Then><Statement><StartPos FileId="F_17" Row="226" Column="24"/><EndPos FileId="F_17" Row="230" Column="21"/></Statement></Then><Else><Statement><StartPos FileId="F_17" Row="233" Column="14"/><EndPos FileId="F_17" Row="233" Column="39"/></Statement><Statement><StartPos FileId="F_17" Row="234" Column="14"/><EndPos FileId="F_17" Row="234" Column="49"/></Statement><Statement><StartPos FileId="F_17" Row="235" Column="14"/><EndPos FileId="F_17" Row="235" Column="52"/></Statement></Else></IfStatement><Statement><StartPos FileId="F_17" Row="238" Column="22"/><EndPos FileId="F_17" Row="238" Column="28"/></Statement></Statements></Paragraph><Paragraph id="P_52" Name="A-EXIT" FallThrough="0"><StartPos FileId="F_17" Row="241" Column="8"/><EndPos FileId="F_17" Row="241" Column="14"/><Statements><ExitStatement><StartPos FileId="F_17" Row="242" Column="12"/><EndPos FileId="F_17" Row="242" Column="16"/></ExitStatement><ExitStatement><StartPos FileId="F_17" Row="243" Column="12"/><EndPos FileId="F_17" Row="243" Column="18"/></ExitStatement></Statements></Paragraph></Section></Sections></FlowChart>
